lazy_type_hint/__init__.py
lazy_type_hint/data_type_tree/__init__.py
lazy_type_hint/data_type_tree/data_type_tree.py
lazy_type_hint/data_type_tree/factory.py
lazy_type_hint/data_type_tree/generic_type/__init__.py
lazy_type_hint/data_type_tree/generic_type/dict_data_type_tree.py
lazy_type_hint/data_type_tree/generic_type/generic_data_type_tree.py
lazy_type_hint/data_type_tree/generic_type/iterator_data_type_tree.py
lazy_type_hint/data_type_tree/generic_type/list_data_type_tree.py
lazy_type_hint/data_type_tree/generic_type/mapping_data_type_tree.py
lazy_type_hint/data_type_tree/generic_type/mapping_proxy_data_type_tree.py
lazy_type_hint/data_type_tree/generic_type/pandas_data_frame_data_type_tree.py
lazy_type_hint/data_type_tree/generic_type/pandas_series_data_type_tree.py
lazy_type_hint/data_type_tree/generic_type/sequence_data_type_tree.py
lazy_type_hint/data_type_tree/generic_type/set_and_sequence_operations.py
lazy_type_hint/data_type_tree/generic_type/set_data_type_tree.py
lazy_type_hint/data_type_tree/generic_type/tuple_data_type_tree.py
lazy_type_hint/data_type_tree/simple_data_type_tree/__init__.py
lazy_type_hint/data_type_tree/simple_data_type_tree/function_data_type_tree.py
lazy_type_hint/data_type_tree/simple_data_type_tree/instance_data_type_tree.py
lazy_type_hint/data_type_tree/simple_data_type_tree/io_data_type_tree.py
lazy_type_hint/data_type_tree/simple_data_type_tree/module_data_type_tree.py
lazy_type_hint/data_type_tree/simple_data_type_tree/numpy_data_type_tree.py
lazy_type_hint/data_type_tree/simple_data_type_tree/simple_data_type_tree.py
lazy_type_hint/data_type_tree/simple_data_type_tree/type_data_type_tree.py
lazy_type_hint/file_modifiers/__init__.py
lazy_type_hint/file_modifiers/py_file_modifier.py
lazy_type_hint/file_modifiers/yaml_file_modifier.py
lazy_type_hint/generators/lazy_type_hint.py
lazy_type_hint/generators/lazy_type_hint_abc.py
lazy_type_hint/generators/lazy_type_hint_live.py
lazy_type_hint/py.typed
lazy_type_hint/strategies.py
lazy_type_hint-3.1.0.dist-info/METADATA
lazy_type_hint-3.1.0.dist-info/WHEEL
lazy_type_hint-3.1.0.dist-info/RECORD
