Metadata-Version: 2.1
Name: lazy-type-hint
Version: 3.1.0
Summary: Automate type hint generation in a single line.
Author: Manuel Floriano Vázquez
Author-email: mflovaa@gmail.com
Requires-Python: >=3.9,<=3.12
Classifier: Programming Language :: Python :: 3
Classifier: Programming Language :: Python :: 3.9
Classifier: Programming Language :: Python :: 3.10
Classifier: Programming Language :: Python :: 3.11
Classifier: Programming Language :: Python :: 3.12
Requires-Dist: typing_extensions
Project-URL: Source, https://github.com/mflova/lazy-type-hint
